<annotation>
	<folder>mcd</folder>
	<filename>232.jpg</filename>
	<path>C:/Users/jp/Desktop/ML/mcd/232.jpg</path>
	<source>
		<database>Unknown</database>
	</source>
	<size>
		<width>615</width>
		<height>461</height>
		<depth>3</depth>
	</size>
	<segmented>0</segmented>
	<object>
		<name>mcd</name>
		<pose>Unspecified</pose>
		<truncated>0</truncated>
		<difficult>0</difficult>
		<bndbox>
			<xmin>167</xmin>
			<ymin>165</ymin>
			<xmax>227</xmax>
			<ymax>223</ymax>
		</bndbox>
	</object>
	<object>
		<name>mcd</name>
		<pose>Unspecified</pose>
		<truncated>0</truncated>
		<difficult>0</difficult>
		<bndbox>
			<xmin>244</xmin>
			<ymin>193</ymin>
			<xmax>432</xmax>
			<ymax>237</ymax>
		</bndbox>
	</object>
</annotation>
